ci/environment.yml
notebooks/demo_environment.yaml
notebooks/reproject_demo.ipynb
notebooks/resample_demo.ipynb
pangeo_forge_ndpyramid/__init__.py
pangeo_forge_ndpyramid/_version.py
pangeo_forge_ndpyramid/common.py
pangeo_forge_ndpyramid/transforms.py
pangeo_forge_ndpyramid-0.0.4.dist-info/LICENSE
pangeo_forge_ndpyramid-0.0.4.dist-info/METADATA
pangeo_forge_ndpyramid-0.0.4.dist-info/WHEEL
pangeo_forge_ndpyramid-0.0.4.dist-info/top_level.txt
pangeo_forge_ndpyramid-0.0.4.dist-info/RECORD
