Metadata-Version: 2.1
Name: pangeo-forge-ndpyramid
Version: 0.0.4
Summary: Pangeo Forge extension libary to generate multi-scale pyramids through pangeo-forge-recipes.
Author-email: CarbonPlan <tech@carbonplan.org>
License: MIT
Classifier: Development Status :: 4 - Beta
Classifier: License :: OSI Approved :: MIT License
Classifier: Operating System :: OS Independent
Classifier: Intended Audience :: Science/Research
Classifier: Programming Language :: Python
Classifier: Programming Language :: Python :: 3
Classifier: Programming Language :: Python :: 3.10
Classifier: Topic :: Scientific/Engineering
Requires-Python: >=3.10
License-File: LICENSE
Requires-Dist: pangeo-forge-recipes
Requires-Dist: ndpyramid
Requires-Dist: dask
Requires-Dist: pyresample
Requires-Dist: rioxarray
Provides-Extra: dynamic
Requires-Dist: version ; extra == 'dynamic'
Provides-Extra: test
Requires-Dist: pre-commit ; extra == 'test'
Requires-Dist: pytest-mypy ; extra == 'test'
Requires-Dist: pytest-cov ; extra == 'test'
Requires-Dist: pytest ; extra == 'test'
Requires-Dist: ruff ; extra == 'test'
Requires-Dist: rioxarray ; extra == 'test'
Requires-Dist: pooch ; extra == 'test'
Requires-Dist: xarray-datatree ; extra == 'test'
